radium/__init__.py
radium/formatter.py
radium/webhook.py
radium-1.0.2.dist-info/LICENSE
radium-1.0.2.dist-info/METADATA
radium-1.0.2.dist-info/WHEEL
radium-1.0.2.dist-info/top_level.txt
radium-1.0.2.dist-info/RECORD
