Metadata-Version: 2.1
Name: radium
Version: 1.0.2
Summary: Supercharge the Python logging module.
Home-page: https://github.com/ja1dan/radium
Author: ja1dan
Author-email: ajaidan0@gmail.com
License: UNKNOWN
Project-URL: Bug Tracker, https://github.com/ja1dan/radium/issues
Platform: UNKNOWN
Classifier: Programming Language :: Python :: 3
Classifier: Operating System :: OS Independent
Requires-Python: >=3.6
License-File: LICENSE
Requires-Dist: aiocache
Requires-Dist: aiohttp
Requires-Dist: ujson
Requires-Dist: msgpack
